signalsdk/__init__.py
signalsdk/api.py
signalsdk/config.py
signalsdk/local_mqtt.py
signalsdk/signal_app.py
signalsdk/signal_exception.py
signalsdk/validator.py
signal_application_python_sdk-3.2.1.dist-info/METADATA
signal_application_python_sdk-3.2.1.dist-info/WHEEL
signal_application_python_sdk-3.2.1.dist-info/top_level.txt
signal_application_python_sdk-3.2.1.dist-info/RECORD
