Metadata-Version: 2.2
Name: signal-application-python-sdk
Version: 3.2.1
Summary: signal application services
Author: Wesley Clover
Author-email: burak.cakmak@wesleyclover.com
Requires-Dist: requests>=2.31.0
Requires-Dist: paho-mqtt==1.6.1
Requires-Dist: urllib3==2.0.7
Requires-Dist: python-dateutil==2.8.2
Dynamic: author
Dynamic: author-email
Dynamic: description
Dynamic: description-content-type
Dynamic: requires-dist
Dynamic: summary
